hyperhyper/__init__.py
hyperhyper/bunch.py
hyperhyper/corpus.py
hyperhyper/evaluation.py
hyperhyper/experiment.py
hyperhyper/pair_counts.py
hyperhyper/pmi.py
hyperhyper/preprocessing.py
hyperhyper/svd.py
hyperhyper/utils.py
hyperhyper/evaluation_datasets/__init__.py
hyperhyper/evaluation_datasets/de/README.txt
hyperhyper/evaluation_datasets/de/__init__.py
hyperhyper/evaluation_datasets/de/analogy/__init__.py
hyperhyper/evaluation_datasets/de/analogy/google.txt
hyperhyper/evaluation_datasets/de/analogy/open.txt
hyperhyper/evaluation_datasets/de/analogy/opposite.txt
hyperhyper/evaluation_datasets/de/analogy/parasem.txt
hyperhyper/evaluation_datasets/de/doesnt_fit/__init__.py
hyperhyper/evaluation_datasets/de/doesnt_fit/de_toefl_subset.txt
hyperhyper/evaluation_datasets/de/doesnt_fit/questions.txt
hyperhyper/evaluation_datasets/de/ws/__init__.py
hyperhyper/evaluation_datasets/de/ws/gur350.txt
hyperhyper/evaluation_datasets/de/ws/gur65.txt
hyperhyper/evaluation_datasets/de/ws/schm280.txt
hyperhyper/evaluation_datasets/de/ws/simlex999.txt
hyperhyper/evaluation_datasets/de/ws/ws353rel.txt
hyperhyper/evaluation_datasets/de/ws/ws353sim.txt
hyperhyper/evaluation_datasets/de/ws/zg222.txt
hyperhyper/evaluation_datasets/en/__init__.py
hyperhyper/evaluation_datasets/en/analogy/__init__.py
hyperhyper/evaluation_datasets/en/analogy/google.txt
hyperhyper/evaluation_datasets/en/analogy/msr.txt
hyperhyper/evaluation_datasets/en/ws/__init__.py
hyperhyper/evaluation_datasets/en/ws/bruni_men.txt
hyperhyper/evaluation_datasets/en/ws/luong_rare.txt
hyperhyper/evaluation_datasets/en/ws/radinsky_mturk.txt
hyperhyper/evaluation_datasets/en/ws/ws353.txt
hyperhyper/evaluation_datasets/en/ws/ws353_relatedness.txt
hyperhyper/evaluation_datasets/en/ws/ws353_similarity.txt
hyperhyper-0.1.1.dist-info/LICENSE
hyperhyper-0.1.1.dist-info/METADATA
hyperhyper-0.1.1.dist-info/WHEEL
hyperhyper-0.1.1.dist-info/top_level.txt
hyperhyper-0.1.1.dist-info/zip-safe
hyperhyper-0.1.1.dist-info/RECORD
