Metadata-Version: 2.1
Name: hyperhyper
Version: 0.1.1
Summary: Python Library to Construct Word Embeddings for Small Data
Home-page: https://github.com/jfilter/hyperhyper
Author: Johannes Filter
Author-email: hi@jfilter.de
License: BSD
Platform: UNKNOWN
Classifier: Programming Language :: Python :: 3.6
Classifier: Programming Language :: Python :: 3.7
Classifier: Programming Language :: Python :: 3.8
Classifier: License :: OSI Approved :: BSD License
Classifier: Topic :: Scientific/Engineering :: Information Analysis
Classifier: Topic :: Scientific/Engineering :: Artificial Intelligence
Requires-Python: >=3.6
Requires-Dist: dataset (==1.*)
Requires-Dist: tqdm
Requires-Dist: gensim (==3.*)
Requires-Dist: importlib-resources ; python_version < "3.7"
Provides-Extra: full
Requires-Dist: spacy (==2.*) ; extra == 'full'
Requires-Dist: scikit-learn ; extra == 'full'
